staticfiles_select2/__init__.py
staticfiles_select2/static/staticfiles_select2/.gitkeep
staticfiles_select2/static/staticfiles_select2/select2/select2_locale_fr.js
staticfiles_select2/static/staticfiles_select2/select2/select2_locale_eu.js
staticfiles_select2/static/staticfiles_select2/select2/select2_locale_hu.js
staticfiles_select2/static/staticfiles_select2/select2/select2_locale_cs.js
staticfiles_select2/static/staticfiles_select2/select2/select2_locale_is.js
staticfiles_select2/static/staticfiles_select2/select2/select2_locale_zh-CN.js
staticfiles_select2/static/staticfiles_select2/select2/select2_locale_lv.js
staticfiles_select2/static/staticfiles_select2/select2/select2_locale_id.js
staticfiles_select2/static/staticfiles_select2/select2/select2_locale_en.js.template
staticfiles_select2/static/staticfiles_select2/select2/select2_locale_pl.js
staticfiles_select2/static/staticfiles_select2/select2/select2_locale_es.js
staticfiles_select2/static/staticfiles_select2/select2/select2_locale_th.js
staticfiles_select2/static/staticfiles_select2/select2/select2_locale_ua.js
staticfiles_select2/static/staticfiles_select2/select2/select2_locale_zh-TW.js
staticfiles_select2/static/staticfiles_select2/select2/README.md
staticfiles_select2/static/staticfiles_select2/select2/select2_locale_no.js
staticfiles_select2/static/staticfiles_select2/select2/select2_locale_mk.js
staticfiles_select2/static/staticfiles_select2/select2/select2_locale_ja.js
staticfiles_select2/static/staticfiles_select2/select2/select2_locale_it.js
staticfiles_select2/static/staticfiles_select2/select2/select2_locale_ru.js
staticfiles_select2/static/staticfiles_select2/select2/LICENSE
staticfiles_select2/static/staticfiles_select2/select2/select2_locale_et.js
staticfiles_select2/static/staticfiles_select2/select2/select2_locale_de.js
staticfiles_select2/static/staticfiles_select2/select2/select2_locale_gl.js
django_staticfiles_select2-3.4.5.dist-info/METADATA
django_staticfiles_select2-3.4.5.dist-info/top_level.txt
django_staticfiles_select2-3.4.5.dist-info/pydist.json
django_staticfiles_select2-3.4.5.dist-info/RECORD
django_staticfiles_select2-3.4.5.dist-info/WHEEL
django_staticfiles_select2-3.4.5.dist-info/DESCRIPTION.rst
