Metadata-Version: 2.0
Name: django-staticfiles-select2
Version: 3.4.5
Summary: select2 meets Django staticfiles
Home-page: http://bitbucket.org/slafs/django-staticfiles-select2/
Author: Slawek Ehlert
Author-email: slafs@op.pl
License: UNKNOWN
Platform: UNKNOWN
Classifier: Development Status :: 4 - Beta
Classifier: Environment :: Web Environment
Classifier: Intended Audience :: Developers
Classifier: License :: OSI Approved :: BSD License
Classifier: Operating System :: OS Independent
Classifier: Programming Language :: Python
Classifier: Topic :: Software Development :: Libraries :: Python Modules
Classifier: Topic :: Utilities
Classifier: Programming Language :: Python
Classifier: Programming Language :: Python :: 2.6
Classifier: Programming Language :: Python :: 2.7
